LICENSE
MANIFEST.in
README.md
pyproject.toml
src/sunbather/RT.py
src/sunbather/__init__.py
src/sunbather/construct_parker.py
src/sunbather/convergeT_parker.py
src/sunbather/install_cloudy.py
src/sunbather/solveT.py
src/sunbather/species_enlim.txt
src/sunbather/tools.py
src/sunbather.egg-info/PKG-INFO
src/sunbather.egg-info/SOURCES.txt
src/sunbather.egg-info/dependency_links.txt
src/sunbather.egg-info/requires.txt
src/sunbather.egg-info/top_level.txt
src/sunbather/RT_tables/Al+10_levels_NIST.txt
src/sunbather/RT_tables/Al+10_levels_processed.txt
src/sunbather/RT_tables/Al+10_lines_NIST.txt
src/sunbather/RT_tables/Al+11_levels_NIST.txt
src/sunbather/RT_tables/Al+11_levels_processed.txt
src/sunbather/RT_tables/Al+11_lines_NIST.txt
src/sunbather/RT_tables/Al+12_levels_NIST.txt
src/sunbather/RT_tables/Al+12_levels_processed.txt
src/sunbather/RT_tables/Al+12_lines_NIST.txt
src/sunbather/RT_tables/Al+2_levels_NIST.txt
src/sunbather/RT_tables/Al+2_levels_processed.txt
src/sunbather/RT_tables/Al+2_lines_NIST.txt
src/sunbather/RT_tables/Al+3_levels_NIST.txt
src/sunbather/RT_tables/Al+3_levels_processed.txt
src/sunbather/RT_tables/Al+3_lines_NIST.txt
src/sunbather/RT_tables/Al+4_levels_NIST.txt
src/sunbather/RT_tables/Al+4_levels_processed.txt
src/sunbather/RT_tables/Al+4_lines_NIST.txt
src/sunbather/RT_tables/Al+5_levels_NIST.txt
src/sunbather/RT_tables/Al+5_levels_processed.txt
src/sunbather/RT_tables/Al+5_lines_NIST.txt
src/sunbather/RT_tables/Al+6_levels_NIST.txt
src/sunbather/RT_tables/Al+6_levels_processed.txt
src/sunbather/RT_tables/Al+6_lines_NIST.txt
src/sunbather/RT_tables/Al+7_levels_NIST.txt
src/sunbather/RT_tables/Al+7_levels_processed.txt
src/sunbather/RT_tables/Al+7_lines_NIST.txt
src/sunbather/RT_tables/Al+8_levels_NIST.txt
src/sunbather/RT_tables/Al+8_levels_processed.txt
src/sunbather/RT_tables/Al+8_lines_NIST.txt
src/sunbather/RT_tables/Al+9_levels_NIST.txt
src/sunbather/RT_tables/Al+9_levels_processed.txt
src/sunbather/RT_tables/Al+9_lines_NIST.txt
src/sunbather/RT_tables/Al+_levels_NIST.txt
src/sunbather/RT_tables/Al+_levels_processed.txt
src/sunbather/RT_tables/Al+_lines_NIST.txt
src/sunbather/RT_tables/Al_levels_NIST.txt
