Metadata-Version: 2.2
Name: sunbather
Version: 1.0.0
Summary: sunbather
Author-email: Dion Linssen <d.c.linssen@uva.nl>, Antonija Oklopčić <a.oklopcic@uva.nl>, Steven Rieder <s.rieder@uva.nl>
License: MIT License
Project-URL: Issues, https://github.com/antonpannekoek/sunbather/issues
Project-URL: Repository, https://github.com/antonpannekoek/sunbather
Keywords: astrophysics
Requires-Python: >=3.9
License-File: LICENSE
Requires-Dist: numpy<3,>=1.24.3
Requires-Dist: pandas<3,>=1.1.4
Requires-Dist: matplotlib<4,>=3.7.1
Requires-Dist: scipy<1.14,>=1.9.0
Requires-Dist: astropy<7,>=5.0
Requires-Dist: p-winds<2,>=1.3.4
